{
  "form_title": "Incident report",
  "recipient_email": "youvictorfc@gmail.com",
  "minto_email": "hello@mintodisabilityservices.com.au",
  "timestamp": "2025-03-31T13:06:19.149003",
  "pdf_path": "/home/runner/workspace/uploads/submitted_forms/Incident_report/20250331_130619/Incident_report_form10_user1_20250331130618.pdf",
  "form_data": {
    "form_id": 10,
    "form_title": "Incident report",
    "user_id": 1,
    "user_email": "youvictorfc@gmail.com",
    "user_name": "victor",
    "submitted_at": "2025-03-31T13:06:19.145550",
    "question_count": 30,
    "answered_count": 30
  }
}